{"id":"5359a3d3-8b6e-4fe4-88ab-b070044a8fe3","timestamp":1751982371913,"matcher":{"static":{},"wildcard":{},"dynamic":{}},"prerendered":["/mariage/richy","/mariage/futursmaries","/mariage/mumsiepascal","/mariage/maminou","/slides/javascript","/mariage/mumsiepascal/answer","/mariage/futursmaries/answer","/mariage/maminou/answer","/mariage/richy/answer","/en/mariage/mumsiepascal","/en/mariage/maminou","/en/mariage/richy","/en/mariage/futursmaries/answer","/en/mariage/futursmaries","/en/mariage/mumsiepascal/answer","/en/mariage/maminou/answer","/en/mariage/richy/answer","/mariage/lulufamily","/en/mariage/lulufamily","/mariage/lulufamily/answer","/en/mariage/lulufamily/answer","/en/mariage/empegues","/mariage/empegues/answer","/mariage/empegues","/en/mariage/empegues/answer","/en/mariage/mathourom","/mariage/mathourom","/en/mariage/mathourom/answer","/mariage/mathourom/answer","/en/mariage/maya","/mariage/maya/answer","/mariage/maya","/en/mariage/maya/answer","/mariage/biboune","/en/mariage/biboune","/mariage/biboune/answer","/en/mariage/biboune/answer","/mariage/joeva","/mariage/joeva/answer","/en/mariage/joeva","/mariage/gmgd","/en/mariage/gmgd","/en/mariage/joeva/answer","/mariage/gmgd/answer","/en/mariage/gmgd/answer","/en/mariage/mepe","/mariage/mepe","/en/mariage/mepe/answer","/mariage/mepe/answer","/mariage/tanteadele","/mariage/tanteadele/answer","/en/mariage/tanteadele","/mariage/auntiemoni","/mariage/auntiemoni/answer","/en/mariage/tanteadele/answer","/en/mariage/auntiemoni","/en/mariage/auntiemoni/answer","/mariage/mamieva","/en/mariage/mamieva","/mariage/mamieva/answer","/mariage/mulots","/en/mariage/mamieva/answer","/en/mariage/mulots","/mariage/mulots/answer","/mariage/auntiesismark","/en/mariage/mulots/answer","/mariage/auntiesismark/answer","/en/mariage/auntiesismark","/en/mariage/auntiesismark/answer","/mariage/plauds","/en/mariage/plauds","/en/mariage/plauds/answer","/mariage/plauds/answer","/mariage/parrain","/en/mariage/parrain","/mariage/parrain/answer","/en/mariage/parrain/answer","/mariage/tatajaja","/en/mariage/tatajaja/answer","/mariage/tatajaja/answer","/en/mariage/tatajaja","/mariage/abeilles","/en/mariage/abeilles","/mariage/abeilles/answer","/en/mariage/abeilles/answer","/en/mariage/airbnb","/mariage/airbnb","/mariage/fin","/en/mariage/airbnb/answer","/mariage/airbnb/answer","/en/mariage/fin","/mariage/fin/answer","/en/mariage/fin/answer","/mariage/stew","/en/mariage/stew","/mariage/stew/answer","/en/mariage/stew/answer","/mariage/voilier","/mariage/voilier/answer","/en/mariage/voilier","/en/mariage/voilier/answer","/mariage/pauline","/en/mariage/pauline","/mariage/tomtom","/en/mariage/pauline/answer","/en/mariage/tomtom","/mariage/pauline/answer","/mariage/tomtom/answer","/en/mariage/tomtom/answer","/en/mariage/claquesdtg","/en/mariage/claquesdtg/answer","/mariage/claquesdtg","/mariage/filleule","/mariage/claquesdtg/answer","/mariage/filleule/answer","/en/mariage/filleule","/mariage/fleur/answer","/mariage/fleur","/en/mariage/filleule/answer","/en/mariage/fleur/answer","/en/mariage/fleur","/mariage/marine","/en/mariage/marine","/en/mariage/marine/answer","/mariage/marine/answer","/mariage/anne","/en/mariage/anne","/mariage/anne/answer","/en/mariage/anne/answer","/mariage/nicoise","/en/mariage/nicoise","/en/mariage/nicoise/answer","/mariage/nicoise/answer","/mariage/rush","/en/mariage/rush","/en/mariage/rush/answer","/mariage/rush/answer","/mariage/florence","/mariage/florence/answer","/en/mariage/florence","/mariage/hoarau/answer","/en/mariage/hoarau","/en/mariage/florence/answer","/mariage/hoarau","/mariage/soireebde","/en/mariage/hoarau/answer","/en/mariage/soireebde","/mariage/soireebde/answer","/mariage/john","/en/mariage/soireebde/answer","/en/mariage/john","/mariage/john/answer","/en/mariage/john/answer","/mariage/obrigado","/en/mariage/obrigado","/mariage/obrigado/answer","/mariage/miami2","/en/mariage/obrigado/answer","/en/mariage/miami2","/mariage/miami2/answer","/mariage/ephebe","/en/mariage/ephebe","/en/mariage/miami2/answer","/mariage/ephebe/answer","/en/mariage/ephebe/answer","/mariage/lolocaillou","/en/mariage/lolocaillou","/en/mariage/lolocaillou/answer","/en/mariage/nigzyfamily","/mariage/lolocaillou/answer","/mariage/nigzyfamily","/mariage/nigzyfamily/answer","/en/mariage/nigzyfamily/answer","/en/mariage/lilyflojuju","/mariage/lilyflojuju","/en/mariage/lilyflojuju/answer","/mariage/lilyflojuju/answer","/en/mariage/colombes","/mariage/colombes","/mariage/colombes/answer","/en/mariage/colombes/answer","/en/mariage/flosimon","/mariage/flosimon","/mariage/malou","/mariage/flosimon/answer","/en/mariage/flosimon/answer","/en/mariage/malou","/mariage/malou/answer","/en/mariage/malou/answer","/mariage/mathias","/en/mariage/mathias","/mariage/mathias/answer","/en/mariage/mathias/answer","/mariage/kaga","/en/mariage/kaga","/mariage/kaga/answer","/en/mariage/kaga/answer","/en/mariage/orny","/en/mariage/orny/answer","/mariage/orny","/mariage/orny/answer","/mariage/cocopepito","/mariage/cocopepito/answer","/en/mariage/cocopepito","/en/mariage/cocopepito/answer","/mariage/mae","/mariage/mae/answer","/en/mariage/mae","/en/mariage/mae/answer","/mariage/jess","/en/mariage/jess","/mariage/jess/answer","/en/mariage/jess/answer","/mariage/mrmrsd/answer","/en/mariage/mrmrsd","/mariage/mrmrsd","/en/mariage/mrmrsd/answer","/mariage/jeanluc","/en/mariage/jeanluc","/mariage/jeanluc/answer","/mariage/lelandais","/en/mariage/jeanluc/answer","/en/mariage/lelandais","/mariage/lelandais/answer","/en/mariage/lelandais/answer","/mariage/annick","/en/mariage/annick","/mariage/annick/answer","/mariage/sylvie","/en/mariage/annick/answer","/en/mariage/sylvie","/en/mariage/sylvie/answer","/mariage/sylvie/answer","/mariage/mariawojtek","/mariage/mariawojtek/answer","/en/mariage/mariawojtek","/en/mariage/mariawojtek/answer","/mariage/marjf","/mariage/marjf/answer","/en/mariage/marjf","/en/mariage/marjf/answer","/mariage/mrsbouche","/en/mariage/mrsbouche","/mariage/ganou","/mariage/mrsbouche/answer","/en/mariage/mrsbouche/answer","/en/mariage/ganou","/en/mariage/ganou/answer","/mariage/ganou/answer","/en/mariage/labarbiniere","/mariage/labarbiniere","/en/mariage/labarbiniere/answer","/mariage/labarbiniere/answer","/en/slides/javascript","/mariage/adm","/en/mariage/adm","/mariage/church","/en/mariage/church","/afterworks","/en/afterworks","/agnes","/en/agnes","/activities","/en/activities","/courses","/en/courses","/","/en","/articles","/mariage/merci","/en/articles","/en/mariage/merci","/mariage","/en/mariage","/mariage/design","/en/mariage/design","/mariage/photo","/en/mariage/photo","/mariage/menu","/en/mariage/menu","/en/talks","/talks","/en/design","/design","/articles/react-test-refactoring-snapshot","/en/articles/react-test-refactoring-snapshot"]}